tpk/__about__.py
tpk/__init__.py
tpk/__main__.py
tpk/cli.py
tpk/hypervalidation/__init__.py
tpk/hypervalidation/hyperparameter_search.py
tpk/hypervalidation/model_train.py
tpk/model/__init__.py
tpk/model/estimator.py
tpk/model/lightning_module.py
tpk/model/module.py
tpk/testing/__init__.py
tpk/testing/datasets/__init__.py
tpk/testing/datasets/m5/__init__.py
tpk/testing/datasets/m5/accuracy_evaluator.py
tpk/testing/datasets/m5/load_dataset.py
tpk/utils/__init__.py
tpk/utils/dataset.py
tpk-0.0.1.dev0.dist-info/METADATA
tpk-0.0.1.dev0.dist-info/WHEEL
tpk-0.0.1.dev0.dist-info/entry_points.txt
tpk-0.0.1.dev0.dist-info/licenses/LICENSE
tpk-0.0.1.dev0.dist-info/RECORD
