Metadata-Version: 2.1
Name: tpk
Version: 0.0.1.dev0
Summary: TempportalPredictionsKit: toolset for timeseries data predictions
Project-URL: Homepage, https://tpk.airt.ai/
Project-URL: Documentation, https://tpk.airt.ai/latest/getting-started/
Project-URL: Tracker, https://github.com/airtai/tpk/issues
Project-URL: Source, https://github.com/airtai/tpk
Author-email: airt <info@airt.ai>
License-File: LICENSE
Keywords: machine learning,timeseries
Classifier: Development Status :: 5 - Production/Stable
Classifier: Environment :: Web Environment
Classifier: Intended Audience :: Developers
Classifier: Intended Audience :: Information Technology
Classifier: Intended Audience :: System Administrators
Classifier: License :: OSI Approved :: Apache Software License
Classifier: Operating System :: OS Independent
Classifier: Programming Language :: Python
Classifier: Programming Language :: Python :: 3
Classifier: Programming Language :: Python :: 3 :: Only
Classifier: Programming Language :: Python :: 3.8
Classifier: Programming Language :: Python :: 3.9
Classifier: Programming Language :: Python :: 3.10
Classifier: Programming Language :: Python :: 3.11
Classifier: Programming Language :: Python :: 3.12
Classifier: Programming Language :: Python :: Implementation :: CPython
Classifier: Topic :: Internet
Classifier: Topic :: Software Development
Classifier: Topic :: Software Development :: Libraries
Classifier: Topic :: Software Development :: Libraries :: Application Frameworks
Classifier: Topic :: Software Development :: Libraries :: Python Modules
Classifier: Typing :: Typed
Requires-Python: >=3.8
Requires-Dist: asyncer>=0.0.2
Requires-Dist: gluonts[torch]>=0.14.1
Requires-Dist: optuna-dashboard>=0.12.0
Requires-Dist: optuna>=3.3.0
Requires-Dist: tqdm
Requires-Dist: typer>=0.9.0
Requires-Dist: ujson>=5.8.0
Provides-Extra: dev
Requires-Dist: detect-secrets==1.4.0; extra == 'dev'
Requires-Dist: pre-commit==3.5.0; extra == 'dev'
Requires-Dist: tpk[devdocs,lint,testing]; extra == 'dev'
Provides-Extra: devdocs
Requires-Dist: cairosvg; extra == 'devdocs'
Requires-Dist: mdx-include<2,>=1.4.1; extra == 'devdocs'
Requires-Dist: mike<3,>=2; extra == 'devdocs'
Requires-Dist: mkdocs-git-revision-date-localized-plugin>=1.2.0; extra == 'devdocs'
Requires-Dist: mkdocs-glightbox==0.3.5; extra == 'devdocs'
Requires-Dist: mkdocs-literate-nav>=0.6.0; extra == 'devdocs'
Requires-Dist: mkdocs-macros-plugin>=1.0.0; extra == 'devdocs'
Requires-Dist: mkdocs-material<10,>=9; extra == 'devdocs'
Requires-Dist: mkdocs-minify-plugin>=0.7.1; extra == 'devdocs'
Requires-Dist: mkdocs-static-i18n<2,>=1; extra == 'devdocs'
Requires-Dist: mkdocstrings[python]>=0.23.0; extra == 'devdocs'
Requires-Dist: pillow; extra == 'devdocs'
Requires-Dist: typer>=0.9.0; extra == 'devdocs'
Provides-Extra: lint
Requires-Dist: bandit==1.7.6; extra == 'lint'
Requires-Dist: black==23.11.0; extra == 'lint'
Requires-Dist: isort>=5; extra == 'lint'
Requires-Dist: mypy==1.7.1; extra == 'lint'
Requires-Dist: pyupgrade-directories; extra == 'lint'
Requires-Dist: ruff==0.1.7; extra == 'lint'
Requires-Dist: semgrep==1.50.0; extra == 'lint'
Requires-Dist: types-docutils; extra == 'lint'
Requires-Dist: types-pygments; extra == 'lint'
Requires-Dist: types-pyyaml; extra == 'lint'
Requires-Dist: types-setuptools; extra == 'lint'
Requires-Dist: types-tqdm; extra == 'lint'
Requires-Dist: types-ujson; extra == 'lint'
Provides-Extra: testing
Requires-Dist: coverage[toml]<8,>=7.2; extra == 'testing'
Requires-Dist: dirty-equals==0.7.1; extra == 'testing'
Requires-Dist: pytest-asyncio>=0.21; extra == 'testing'
Requires-Dist: pytest-asyncio>=0.21.0; extra == 'testing'
Requires-Dist: pytest<8,==7.4.3; extra == 'testing'
